jllm/__init__.py
jllm/ckpt_to_hf.py
jllm/nolora_ckpt_to_hf.py
jllm/raw_to_ids.py
jllm/repartition.py
jllm/repartition.sh
jllm/shuffle_datasets.py
jllm/train_pipe.py
jllm/trainer.cpython-311-x86_64-linux-gnu.so
jllm/utils.py
jllm/data/__init__.py
jllm/data/utils.cpython-311-x86_64-linux-gnu.so
jllm/model/__init__.py
jllm/model/lora.py
jllm/model/baichuan/__init__.py
jllm/model/baichuan/configuration_baichuan.py
jllm/model/baichuan/modeling_baichuan.py
jllm/model/baichuan/pipeline_baichuan.cpython-311-x86_64-linux-gnu.so
jllm/model/llama/__init__.py
jllm/model/llama/pipeline_llama.cpython-311-x86_64-linux-gnu.so
jllm/model/qwen/__init__.py
jllm/model/qwen/configuration_qwen.py
jllm/model/qwen/modeling_qwen.py
jllm/model/qwen/pipeline_qwen.cpython-311-x86_64-linux-gnu.so
jllm-1.1.4.dist-info/LICENSE
jllm-1.1.4.dist-info/METADATA
jllm-1.1.4.dist-info/WHEEL
jllm-1.1.4.dist-info/top_level.txt
jllm-1.1.4.dist-info/RECORD
