Metadata-Version: 2.1
Name: jllm
Version: 1.1.4
Summary: Running Large Language Model easily, faster and low-cost
Home-page: https://github.com/janelu9/EasyLLM
Author: Jian Lu
License: Apache 2.0
Project-URL: Homepage, https://github.com/janelu9/EasyLLM
Classifier: Programming Language :: Python :: 3.11
Classifier: License :: OSI Approved :: Apache Software License
Classifier: Topic :: Scientific/Engineering :: Artificial Intelligence
Requires-Python: >=3.11
License-File: LICENSE
Requires-Dist: deepspeed
Requires-Dist: protobuf (==3.20.3)
Requires-Dist: sentencepiece
Requires-Dist: transformers
Requires-Dist: pyarrow
Requires-Dist: tiktoken
